README.md
setup.py
heds/__init__.py
heds/adm1.csv
heds/cmp1.csv
heds/crs1.csv
heds/data.py
heds/enr1.csv
heds.egg-info/PKG-INFO
heds.egg-info/SOURCES.txt
heds.egg-info/dependency_links.txt
heds.egg-info/requires.txt
heds.egg-info/top_level.txt