Metadata-Version: 2.1
Name: heds
Version: 0.1
Summary: A simple package containing a CSV dataset
Author: Gurucharan Raju
Author-email: Gurucharan.Raju-SA@csulb.edu
License: MIT
